{
  "count": 48,
  "next": null,
  "previous": null,
  "results": [
    {
      "id": 77431,
      "inv_part_id": 77431,
      "part": {
        "part_num": "54200",
        "name": "Slope 30\u00b0 1 x 1 x 2/3 (Cheese Slope)",
        "part_cat_id": 3,
        "part_url": "https://rebrickable.com/parts/54200/slope-30-1-x-1-x-23-cheese-slope/",
        "part_img_url": "https://cdn.rebrickable.com/media/parts/elements/4244366.jpg",
        "external_ids": {
          "BrickLink": [
            "54200"
          ],
          "BrickOwl": [
            "158788"
          ],
          "Brickset": [
            "18862",
            "33847",
            "35338",
            "50746",
            "54200",
            "63290"
          ],
          "LDraw": [
            "54200"
          ],
          "LEGO": [
            "18862",
            "33847",
            "35338",
            "50746",
            "54200",
            "63290"
          ]
        },
        "print_of": null
      },
      "color": {
        "id": 33,
        "name": "Trans-Dark Blue",
        "rgb": "0020A0",
        "is_trans": true
      },
      "set_num": "40010-1",
      "quantity": 2,
      "is_spare": false,
      "element_id": "6245256",
      "num_sets": 179
    },
    {
      "id": 86425,
      "inv_part_id": 86425,
      "part": {
        "part_num": "6141",
        "name": "Plate Round 1 x 1 with Solid Stud",
        "part_cat_id": 21,
        "part_url": "https://rebrickable.com/parts/6141/plate-round-1-x-1-with-solid-stud/",
        "part_img_url": "https://cdn.rebrickable.com/media/parts/elements/614126.jpg",
        "external_ids": {
          "BrickLink": [
            "4073"
          ],
          "BrickOwl": [
            "961948"
          ],
          "Brickset": [
            "15570",
            "30057",
            "34823",
            "39799",
            "44325",
            "6141"
          ],
          "LDraw": [
            "4073",
            "6141"
          ],
          "LEGO": [
            "15570",
            "30057",
            "34823",
            "39799",
            "44325",
            "51809",
            "6141"
          ],
          "Peeron": [
            "4073"
          ]
        },
        "print_of": null
      },
      "color": {
        "id": 0,
        "name": "Black",
        "rgb": "05131D",
        "is_trans": false
      },
      "set_num": "40010-1",
      "quantity": 1,
      "is_spare": false,
      "element_id": "614126",
      "num_sets": 1352
    },
    {
      "id": 451279,
      "inv_part_id": 451279,
      "part": {
        "part_num": "54200",
        "name": "Slope 30\u00b0 1 x 1 x 2/3 (Cheese Slope)",
        "part_cat_id": 3,
        "part_url": "https://rebrickable.com/parts/54200/slope-30-1-x-1-x-23-cheese-slope/",
        "part_img_url": "https://cdn.rebrickable.com/media/parts/elements/4244366.jpg",
        "external_ids": {
          "BrickLink": [
            "54200"
          ],
          "BrickOwl": [
            "158788"
          ],
          "Brickset": [
            "18862",
            "33847",
            "35338",
            "50746",
            "54200",
            "63290"
          ],
          "LDraw": [
            "54200"
          ],
          "LEGO": [
            "18862",
            "33847",
            "35338",
            "50746",
            "54200",
            "63290"
          ]
        },
        "print_of": null
      },
      "color": {
        "id": 33,
        "name": "Trans-Dark Blue",
        "rgb": "0020A0",
        "is_trans": true
      },
      "set_num": "40010-1",
      "quantity": 1,
      "is_spare": true,
      "element_id": "6245256",
      "num_sets": 179
    },
    {
      "id": 202193,
      "inv_part_id": 202193,
      "part": {
        "part_num": "41769",
        "name": "Wedge Plate 4 x 2 Right",
        "part_cat_id": 49,
        "part_url": "https://rebrickable.com/parts/41769/wedge-plate-4-x-2-right/",
        "part_img_url": "https://cdn.rebrickable.com/media/parts/elements/4205469.jpg",
        "external_ids": {
          "BrickLink": [
            "41769"
          ],
          "BrickOwl": [
            "886867"
          ],
          "Brickset": [
            "41769",
            "63330"
          ],
          "LDraw": [
            "41769"
          ],
          "LEGO": [
            "41769",
            "63330"
          ]
        },
        "print_of": null
      },
      "color": {
        "id": 70,
        "name": "Reddish Brown",
        "rgb": "582A12",
        "is_trans": false
      },
      "set_num": "40010-1",
      "quantity": 1,
      "is_spare": false,
      "element_id": "4205469",
      "num_sets": 89
    },
    {
      "id": 3602,
      "inv_part_id": 3602,
      "part": {
        "part_num": "48729b",
        "name": "Bar 1L with Clip [Cut Edges and One Side Hole] [Gap in Clip]",
        "part_cat_id": 32,
        "part_url": "https://rebrickable.com/parts/48729b/bar-1l-with-clip-cut-edges-and-one-side-hole-gap-in-clip/",
        "part_img_url": "https://cdn.rebrickable.com/media/parts/elements/4289538.jpg",
        "external_ids": {
          "BrickLink": [
            "48729b"
          ],
          "BrickOwl": [
            "664516"
          ],
          "Brickset": [
            "41005",
            "48729",
            "55529",
            "86022",
            "88428"
          ],
          "LDraw": [
            "48729b"
          ],
          "LEGO": [
            "41005",
            "48729",
            "55529",
            "86022",
            "88428"
          ]
        },
        "print_of": null
      },
      "color": {
        "id": 0,
        "name": "Black",
        "rgb": "05131D",
        "is_trans": false
      },
      "set_num": "40010-1",
      "quantity": 1,
      "is_spare": true,
      "element_id": "6278152",
      "num_sets": 399
    },
    {
      "id": 578552,
      "inv_part_id": 578552,
      "part": {
        "part_num": "3023",
        "name": "Plate 1 x 2",
        "part_cat_id": 14,
        "part_url": "https://rebrickable.com/parts/3023/plate-1-x-2/",
        "part_img_url": "https://cdn.rebrickable.com/media/parts/elements/302323.jpg",
        "external_ids": {
          "BrickLink": [
            "3023"
          ],
          "BrickOwl": [
            "44980"
          ],
          "Brickset": [
            "28653",
            "3023",
            "6225"
          ],
          "LDraw": [
            "28653",
            "3023b"
          ],
          "LEGO": [
            "28653",
            "3023",
            "6225"
          ]
        },
        "print_of": null
      },
      "color": {
        "id": 1,
        "name": "Blue",
        "rgb": "0055BF",
        "is_trans": false
      },
      "set_num": "40010-1",
      "quantity": 2,
      "is_spare": false,
      "element_id": "302323",
      "num_sets": 1032
    },
    {
      "id": 643876,
      "inv_part_id": 643876,
      "part": {
        "part_num": "3023",
        "name": "Plate 1 x 2",
        "part_cat_id": 14,
        "part_url": "https://rebrickable.com/parts/3023/plate-1-x-2/",
        "part_img_url": "https://cdn.rebrickable.com/media/parts/elements/302321.jpg",
        "external_ids": {
          "BrickLink": [
            "3023"
          ],
          "BrickOwl": [
            "44980"
          ],
          "Brickset": [
            "28653",
            "3023",
            "6225"
          ],
          "LDraw": [
            "28653",
            "3023b"
          ],
          "LEGO": [
            "28653",
            "3023",
            "6225"
          ]
        },
        "print_of": null
      },
      "color": {
        "id": 4,
        "name": "Red",
        "rgb": "C91A09",
        "is_trans": false
      },
      "set_num": "40010-1",
      "quantity": 1,
      "is_spare": false,
      "element_id": "302321",
      "num_sets": 1747
    },
    {
      "id": 896259,
      "inv_part_id": 896259,
      "part": {
        "part_num": "3660",
        "name": "Slope Inverted 45\u00b0 2 x 2 [Ovoid Bottom Pin, Bar-sized Stud Holes]",
        "part_cat_id": 3,
        "part_url": "https://rebrickable.com/parts/3660/slope-inverted-45-2-x-2-ovoid-bottom-pin-bar-sized-stud-holes/",
        "part_img_url": "https://cdn.rebrickable.com/media/parts/elements/366021.jpg",
        "external_ids": {
          "BrickLink": [
            "3660"
          ],
          "BrickOwl": [
            "384426"
          ],
          "Brickset": [
            "3660"
          ],
          "LDraw": [
            "3660b",
            "3660c"
          ],
          "LEGO": [
            "3660"
          ]
        },
        "print_of": null
      },
      "color": {
        "id": 4,
        "name": "Red",
        "rgb": "C91A09",
        "is_trans": false
      },
      "set_num": "40010-1",
      "quantity": 1,
      "is_spare": false,
      "element_id": "366021",
      "num_sets": 445
    },
    {
      "id": 429425,
      "inv_part_id": 429425,
      "part": {
        "part_num": "32028",
        "name": "Plate Special 1 x 2 with Door Rail",
        "part_cat_id": 9,
        "part_url": "https://rebrickable.com/parts/32028/plate-special-1-x-2-with-door-rail/",
        "part_img_url": "https://cdn.rebrickable.com/media/parts/elements/4170253.jpg",
        "external_ids": {
          "BrickLink": [
            "32028"
          ],
          "BrickOwl": [
            "148319"
          ],
          "Brickset": [
            "32028"
          ],
          "LDraw": [
            "32028"
          ],
          "LEGO": [
            "32028"
          ]
        },
        "print_of": null
      },
      "color": {
        "id": 15,
        "name": "White",
        "rgb": "FFFFFF",
        "is_trans": false
      },
      "set_num": "40010-1",
      "quantity": 1,
      "is_spare": false,
      "element_id": "6550168",
      "num_sets": 301
    },
    {
      "id": 589951,
      "inv_part_id": 589951,
      "part": {
        "part_num": "4733",
        "name": "Brick Special 1 x 1 Studs on 4 Sides",
        "part_cat_id": 5,
        "part_url": "https://rebrickable.com/parts/4733/brick-special-1-x-1-studs-on-4-sides/",
        "part_img_url": "https://cdn.rebrickable.com/media/parts/elements/4210700.jpg",
        "external_ids": {
          "BrickLink": [
            "4733"
          ],
          "BrickOwl": [
            "14440"
          ],
          "Brickset": [
            "4733"
          ],
          "LDraw": [
            "4733"
          ],
          "LEGO": [
            "4733"
          ]
        },
        "print_of": null
      },
      "color": {
        "id": 72,
        "name": "Dark Bluish Gray",
        "rgb": "6C6E68",
        "is_trans": false
      },
      "set_num": "40010-1",
      "quantity": 2,
      "is_spare": false,
      "element_id": "4210700",
      "num_sets": 195
    },
    {
      "id": 227184,
      "inv_part_id": 227184,
      "part": {
        "part_num": "3024",
        "name": "Plate 1 x 1",
        "part_cat_id": 14,
        "part_url": "https://rebrickable.com/parts/3024/plate-1-x-1/",
        "part_img_url": "https://cdn.rebrickable.com/media/parts/elements/302426.jpg",
        "external_ids": {
          "BrickLink": [
            "3024"
          ],
          "BrickOwl": [
            "322944"
          ],
          "Brickset": [
            "28554",
            "30008",
            "3024",
            "63326"
          ],
          "LDraw": [
            "3024"
          ],
          "LEGO": [
            "28554",
            "30008",
            "3024",
            "63326"
          ],
          "Peeron": [
            "30008"
          ]
        },
        "print_of": null
      },
      "color": {
        "id": 0,
        "name": "Black",
        "rgb": "05131D",
        "is_trans": false
      },
      "set_num": "40010-1",
      "quantity": 2,
      "is_spare": false,
      "element_id": "302426",
      "num_sets": 1228
    },
    {
      "id": 216509,
      "inv_part_id": 216509,
      "part": {
        "part_num": "3024",
        "name": "Plate 1 x 1",
        "part_cat_id": 14,
        "part_url": "https://rebrickable.com/parts/3024/plate-1-x-1/",
        "part_img_url": "https://cdn.rebrickable.com/media/parts/elements/302428.jpg",
        "external_ids": {
          "BrickLink": [
            "3024"
          ],
          "BrickOwl": [
            "322944"
          ],
          "Brickset": [
            "28554",
            "30008",
            "3024",
            "63326"
          ],
          "LDraw": [
            "3024"
          ],
          "LEGO": [
            "28554",
            "30008",
            "3024",
            "63326"
          ],
          "Peeron": [
            "30008"
          ]
        },
        "print_of": null
      },
      "color": {
        "id": 2,
        "name": "Green",
        "rgb": "237841",
        "is_trans": false
      },
      "set_num": "40010-1",
      "quantity": 2,
      "is_spare": false,
      "element_id": "302428",
      "num_sets": 274
    },
    {
      "id": 834348,
      "inv_part_id": 834348,
      "part": {
        "part_num": "12825",
        "name": "Tile Special 1 x 1 with Clip with Rounded Tips",
        "part_cat_id": 15,
        "part_url": "https://rebrickable.com/parts/12825/tile-special-1-x-1-with-clip-with-rounded-tips/",
        "part_img_url": "https://cdn.rebrickable.com/media/parts/elements/6030710.jpg",
        "external_ids": {
          "BrickLink": [
            "2555"
          ],
          "BrickOwl": [
            "369885"
          ],
          "Brickset": [
            "12825"
          ],
          "LDraw": [
            "12825"
          ],
          "LEGO": [
            "12825"
          ]
        },
        "print_of": null
      },
      "color": {
        "id": 72,
        "name": "Dark Bluish Gray",
        "rgb": "6C6E68",
        "is_trans": false
      },
      "set_num": "40010-1",
      "quantity": 2,
      "is_spare": false,
      "element_id": "6030710",
      "num_sets": 104
    },
    {
      "id": 891839,
      "inv_part_id": 891839,
      "part": {
        "part_num": "3659",
        "name": "Brick Arch 1 x 4",
        "part_cat_id": 37,
        "part_url": "https://rebrickable.com/parts/3659/brick-arch-1-x-4/",
        "part_img_url": "https://cdn.rebrickable.com/media/parts/elements/365921.jpg",
        "external_ids": {
          "BrickLink": [
            "3659"
          ],
          "BrickOwl": [
            "813461"
          ],
          "Brickset": [
            "3659"
          ],
          "LDraw": [
            "3659"
          ],
          "LEGO": [
            "3659"
          ]
        },
        "print_of": null
      },
      "color": {
        "id": 4,
        "name": "Red",
        "rgb": "C91A09",
        "is_trans": false
      },
      "set_num": "40010-1",
      "quantity": 2,
      "is_spare": false,
      "element_id": "365921",
      "num_sets": 88
    },
    {
      "id": 390538,
      "inv_part_id": 390538,
      "part": {
        "part_num": "3032",
        "name": "Plate 4 x 6",
        "part_cat_id": 14,
        "part_url": "https://rebrickable.com/parts/3032/plate-4-x-6/",
        "part_img_url": "https://cdn.rebrickable.com/media/parts/elements/303221.jpg",
        "external_ids": {
          "BrickLink": [
            "3032"
          ],
          "BrickOwl": [
            "514495"
          ],
          "Brickset": [
            "3032"
          ],
          "LDraw": [
            "3032"
          ],
          "LEGO": [
            "3032"
          ]
        },
        "print_of": null
      },
      "color": {
        "id": 4,
        "name": "Red",
        "rgb": "C91A09",
        "is_trans": false
      },
      "set_num": "40010-1",
      "quantity": 1,
      "is_spare": false,
      "element_id": "303221",
      "num_sets": 269
    },
    {
      "id": 361940,
      "inv_part_id": 361940,
      "part": {
        "part_num": "3623",
        "name": "Plate 1 x 3",
        "part_cat_id": 14,
        "part_url": "https://rebrickable.com/parts/3623/plate-1-x-3/",
        "part_img_url": "https://cdn.rebrickable.com/media/parts/elements/4107758.jpg",
        "external_ids": {
          "BrickLink": [
            "3623"
          ],
          "BrickOwl": [
            "212990"
          ],
          "Brickset": [
            "3623"
          ],
          "LDraw": [
            "3623"
          ],
          "LEGO": [
            "3623"
          ]
        },
        "print_of": null
      },
      "color": {
        "id": 2,
        "name": "Green",
        "rgb": "237841",
        "is_trans": false
      },
      "set_num": "40010-1",
      "quantity": 1,
      "is_spare": false,
      "element_id": "4107758",
      "num_sets": 250
    },
    {
      "id": 380699,
      "inv_part_id": 380699,
      "part": {
        "part_num": "6141",
        "name": "Plate Round 1 x 1 with Solid Stud",
        "part_cat_id": 21,
        "part_url": "https://rebrickable.com/parts/6141/plate-round-1-x-1-with-solid-stud/",
        "part_img_url": "https://cdn.rebrickable.com/media/parts/elements/614101.jpg",
        "external_ids": {
          "BrickLink": [
            "4073"
          ],
          "BrickOwl": [
            "961948"
          ],
          "Brickset": [
            "15570",
            "30057",
            "34823",
            "39799",
            "44325",
            "6141"
          ],
          "LDraw": [
            "4073",
            "6141"
          ],
          "LEGO": [
            "15570",
            "30057",
            "34823",
            "39799",
            "44325",
            "51809",
            "6141"
          ],
          "Peeron": [
            "4073"
          ]
        },
        "print_of": null
      },
      "color": {
        "id": 15,
        "name": "White",
        "rgb": "FFFFFF",
        "is_trans": false
      },
      "set_num": "40010-1",
      "quantity": 1,
      "is_spare": false,
      "element_id": "614101",
      "num_sets": 1007
    },
    {
      "id": 756534,
      "inv_part_id": 756534,
      "part": {
        "part_num": "30414",
        "name": "Brick Special 1 x 4 with 4 Studs on One Side",
        "part_cat_id": 5,
        "part_url": "https://rebrickable.com/parts/30414/brick-special-1-x-4-with-4-studs-on-one-side/",
        "part_img_url": "https://cdn.rebrickable.com/media/parts/elements/4157223.jpg",
        "external_ids": {
          "BrickLink": [
            "30414"
          ],
          "BrickOwl": [
            "638340"
          ],
          "Brickset": [
            "30414"
          ],
          "LDraw": [
            "30414"
          ],
          "LEGO": [
            "30414"
          ]
        },
        "print_of": null
      },
      "color": {
        "id": 4,
        "name": "Red",
        "rgb": "C91A09",
        "is_trans": false
      },
      "set_num": "40010-1",
      "quantity": 1,
      "is_spare": false,
      "element_id": "4177991",
      "num_sets": 146
    },
    {
      "id": 67105,
      "inv_part_id": 67105,
      "part": {
        "part_num": "3020",
        "name": "Plate 2 x 4",
        "part_cat_id": 14,
        "part_url": "https://rebrickable.com/parts/3020/plate-2-x-4/",
        "part_img_url": "https://cdn.rebrickable.com/media/parts/elements/302021.jpg",
        "external_ids": {
          "BrickLink": [
            "3020"
          ],
          "BrickOwl": [
            "80025"
          ],
          "Brickset": [
            "3020",
            "5584"
          ],
          "LDraw": [
            "3020"
          ],
          "LEGO": [
            "3020",
            "5584"
          ]
        },
        "print_of": null
      },
      "color": {
        "id": 4,
        "name": "Red",
        "rgb": "C91A09",
        "is_trans": false
      },
      "set_num": "40010-1",
      "quantity": 1,
      "is_spare": false,
      "element_id": "302021",
      "num_sets": 1305
    },
    {
      "id": 331459,
      "inv_part_id": 331459,
      "part": {
        "part_num": "6019",
        "name": "Plate Special 1 x 1 with Clip Horizontal [Thick U Clip]",
        "part_cat_id": 9,
        "part_url": "https://rebrickable.com/parts/6019/plate-special-1-x-1-with-clip-horizontal-thick-u-clip/",
        "part_img_url": "https://cdn.rebrickable.com/media/parts/elements/4222034.jpg",
        "external_ids": {
          "BrickLink": [
            "6019"
          ],
          "BrickOwl": [
            "275147"
          ],
          "Brickset": [
            "6019"
          ],
          "LDraw": [
            "6019"
          ],
          "LEGO": [
            "6019"
          ]
        },
        "print_of": null
      },
      "color": {
        "id": 19,
        "name": "Tan",
        "rgb": "E4CD9E",
        "is_trans": false
      },
      "set_num": "40010-1",
      "quantity": 3,
      "is_spare": false,
      "element_id": "601905",
      "num_sets": 16
    },
    {
      "id": 790686,
      "inv_part_id": 790686,
      "part": {
        "part_num": "30374",
        "name": "Bar 4L (Lightsaber Blade / Wand)",
        "part_cat_id": 32,
        "part_url": "https://rebrickable.com/parts/30374/bar-4l-lightsaber-blade-wand/",
        "part_img_url": "https://cdn.rebrickable.com/media/parts/elements/4140303.jpg",
        "external_ids": {
          "BrickLink": [
            "30374"
          ],
          "BrickOwl": [
            "324854"
          ],
          "Brickset": [
            "21462",
            "28697",
            "30374"
          ],
          "LDraw": [
            "30374"
          ],
          "LEGO": [
            "21462",
            "28697",
            "30374"
          ],
          "Peeron": [
            "578"
          ]
        },
        "print_of": null
      },
      "color": {
        "id": 0,
        "name": "Black",
        "rgb": "05131D",
        "is_trans": false
      },
      "set_num": "40010-1",
      "quantity": 1,
      "is_spare": false,
      "element_id": "6116604",
      "num_sets": 552
    },
    {
      "id": 315147,
      "inv_part_id": 315147,
      "part": {
        "part_num": "30375",
        "name": "Torso Mechanical, Battle Droid",
        "part_cat_id": 60,
        "part_url": "https://rebrickable.com/parts/30375/torso-mechanical-battle-droid/",
        "part_img_url": "https://cdn.rebrickable.com/media/parts/elements/4521512.jpg",
        "external_ids": {
          "BrickLink": [
            "30375"
          ],
          "BrickOwl": [
            "148890"
          ],
          "Brickset": [
            "30375",
            "55526",
            "86026"
          ],
          "LDraw": [
            "30375"
          ],
          "LEGO": [
            "30375",
            "55526",
            "86026"
          ]
        },
        "print_of": null
      },
      "color": {
        "id": 72,
        "name": "Dark Bluish Gray",
        "rgb": "6C6E68",
        "is_trans": false
      },
      "set_num": "40010-1",
      "quantity": 1,
      "is_spare": false,
      "element_id": "4521512",
      "num_sets": 70
    },
    {
      "id": 347354,
      "inv_part_id": 347354,
      "part": {
        "part_num": "3023",
        "name": "Plate 1 x 2",
        "part_cat_id": 14,
        "part_url": "https://rebrickable.com/parts/3023/plate-1-x-2/",
        "part_img_url": "https://cdn.rebrickable.com/media/parts/elements/302301.jpg",
        "external_ids": {
          "BrickLink": [
            "3023"
          ],
          "BrickOwl": [
            "44980"
          ],
          "Brickset": [
            "28653",
            "3023",
            "6225"
          ],
          "LDraw": [
            "28653",
            "3023b"
          ],
          "LEGO": [
            "28653",
            "3023",
            "6225"
          ]
        },
        "print_of": null
      },
      "color": {
        "id": 15,
        "name": "White",
        "rgb": "FFFFFF",
        "is_trans": false
      },
      "set_num": "40010-1",
      "quantity": 1,
      "is_spare": false,
      "element_id": "6548261",
      "num_sets": 2323
    },
    {
      "id": 697589,
      "inv_part_id": 697589,
      "part": {
        "part_num": "4286",
        "name": "Slope 33\u00b0 3 x 1",
        "part_cat_id": 3,
        "part_url": "https://rebrickable.com/parts/4286/slope-33-3-x-1/",
        "part_img_url": "https://cdn.rebrickable.com/media/parts/elements/428621.jpg",
        "external_ids": {
          "BrickLink": [
            "4286"
          ],
          "BrickOwl": [
            "226993"
          ],
          "Brickset": [
            "4286"
          ],
          "LDraw": [
            "4286"
          ],
          "LEGO": [
            "4286"
          ]
        },
        "print_of": null
      },
      "color": {
        "id": 4,
        "name": "Red",
        "rgb": "C91A09",
        "is_trans": false
      },
      "set_num": "40010-1",
      "quantity": 3,
      "is_spare": false,
      "element_id": "428621",
      "num_sets": 225
    },
    {
      "id": 649741,
      "inv_part_id": 649741,
      "part": {
        "part_num": "6141",
        "name": "Plate Round 1 x 1 with Solid Stud",
        "part_cat_id": 21,
        "part_url": "https://rebrickable.com/parts/6141/plate-round-1-x-1-with-solid-stud/",
        "part_img_url": "https://cdn.rebrickable.com/media/parts/elements/614124.jpg",
        "external_ids": {
          "BrickLink": [
            "4073"
          ],
          "BrickOwl": [
            "961948"
          ],
          "Brickset": [
            "15570",
            "30057",
            "34823",
            "39799",
            "44325",
            "6141"
          ],
          "LDraw": [
            "4073",
            "6141"
          ],
          "LEGO": [
            "15570",
            "30057",
            "34823",
            "39799",
            "44325",
            "51809",
            "6141"
          ],
          "Peeron": [
            "4073"
          ]
        },
        "print_of": null
      },
      "color": {
        "id": 14,
        "name": "Yellow",
        "rgb": "F2CD37",
        "is_trans": false
      },
      "set_num": "40010-1",
      "quantity": 2,
      "is_spare": false,
      "element_id": "614124",
      "num_sets": 609
    },
    {
      "id": 471074,
      "inv_part_id": 471074,
      "part": {
        "part_num": "3460",
        "name": "Plate 1 x 8",
        "part_cat_id": 14,
        "part_url": "https://rebrickable.com/parts/3460/plate-1-x-8/",
        "part_img_url": "https://cdn.rebrickable.com/media/parts/elements/4210998.jpg",
        "external_ids": {
          "BrickLink": [
            "3460"
          ],
          "BrickOwl": [
            "840367"
          ],
          "Brickset": [
            "3460"
          ],
          "LDraw": [
            "3460"
          ],
          "LEGO": [
            "3460"
          ]
        },
        "print_of": null
      },
      "color": {
        "id": 72,
        "name": "Dark Bluish Gray",
        "rgb": "6C6E68",
        "is_trans": false
      },
      "set_num": "40010-1",
      "quantity": 2,
      "is_spare": false,
      "element_id": "4210998",
      "num_sets": 509
    },
    {
      "id": 336166,
      "inv_part_id": 336166,
      "part": {
        "part_num": "3004pr0001",
        "name": "Brick 1 x 2 with Eyes, Freckles and Smile Print",
        "part_cat_id": 11,
        "part_url": "https://rebrickable.com/parts/3004pr0001/brick-1-x-2-with-eyes-freckles-and-smile-print/",
        "part_img_url": "https://cdn.rebrickable.com/media/parts/elements/4569078.jpg",
        "external_ids": {
          "BrickLink": [
            "3004pb085"
          ],
          "BrickOwl": [
            "321134"
          ],
          "Brickset": [
            "88399"
          ],
          "LEGO": [
            "88399"
          ]
        },
        "print_of": "3004"
      },
      "color": {
        "id": 14,
        "name": "Yellow",
        "rgb": "F2CD37",
        "is_trans": false
      },
      "set_num": "40010-1",
      "quantity": 1,
      "is_spare": false,
      "element_id": "4569078",
      "num_sets": 17
    },
    {
      "id": 756004,
      "inv_part_id": 756004,
      "part": {
        "part_num": "54200",
        "name": "Slope 30\u00b0 1 x 1 x 2/3 (Cheese Slope)",
        "part_cat_id": 3,
        "part_url": "https://rebrickable.com/parts/54200/slope-30-1-x-1-x-23-cheese-slope/",
        "part_img_url": "https://cdn.rebrickable.com/media/parts/elements/4244371.jpg",
        "external_ids": {
          "BrickLink": [
            "54200"
          ],
          "BrickOwl": [
            "158788"
          ],
          "Brickset": [
            "18862",
            "33847",
            "35338",
            "50746",
            "54200",
            "63290"
          ],
          "LDraw": [
            "54200"
          ],
          "LEGO": [
            "18862",
            "33847",
            "35338",
            "50746",
            "54200",
            "63290"
          ]
        },
        "print_of": null
      },
      "color": {
        "id": 4,
        "name": "Red",
        "rgb": "C91A09",
        "is_trans": false
      },
      "set_num": "40010-1",
      "quantity": 1,
      "is_spare": true,
      "element_id": "5074621",
      "num_sets": 514
    },
    {
      "id": 860947,
      "inv_part_id": 860947,
      "part": {
        "part_num": "54200",
        "name": "Slope 30\u00b0 1 x 1 x 2/3 (Cheese Slope)",
        "part_cat_id": 3,
        "part_url": "https://rebrickable.com/parts/54200/slope-30-1-x-1-x-23-cheese-slope/",
        "part_img_url": "https://cdn.rebrickable.com/media/parts/elements/4244371.jpg",
        "external_ids": {
          "BrickLink": [
            "54200"
          ],
          "BrickOwl": [
            "158788"
          ],
          "Brickset": [
            "18862",
            "33847",
            "35338",
            "50746",
            "54200",
            "63290"
          ],
          "LDraw": [
            "54200"
          ],
          "LEGO": [
            "18862",
            "33847",
            "35338",
            "50746",
            "54200",
            "63290"
          ]
        },
        "print_of": null
      },
      "color": {
        "id": 4,
        "name": "Red",
        "rgb": "C91A09",
        "is_trans": false
      },
      "set_num": "40010-1",
      "quantity": 2,
      "is_spare": false,
      "element_id": "5074621",
      "num_sets": 514
    },
    {
      "id": 578509,
      "inv_part_id": 578509,
      "part": {
        "part_num": "2714a",
        "name": "Bar 8L - Two Stop Rings / One  Pin, Technic Figure Ski Pole [Rounded End]",
        "part_cat_id": 32,
        "part_url": "https://rebrickable.com/parts/2714a/bar-8l-two-stop-rings-one-pin-technic-figure-ski-pole-rounded-end/",
        "part_img_url": "https://cdn.rebrickable.com/media/parts/elements/4120251.jpg",
        "external_ids": {
          "BrickLink": [
            "2714a"
          ],
          "BrickOwl": [
            "590943"
          ],
          "Brickset": [
            "2714"
          ],
          "LDraw": [
            "2714a"
          ],
          "LEGO": [
            "2714"
          ],
          "Peeron": [
            "2714"
          ]
        },
        "print_of": null
      },
      "color": {
        "id": 0,
        "name": "Black",
        "rgb": "05131D",
        "is_trans": false
      },
      "set_num": "40010-1",
      "quantity": 2,
      "is_spare": false,
      "element_id": "4120251",
      "num_sets": 19
    },
    {
      "id": 555310,
      "inv_part_id": 555310,
      "part": {
        "part_num": "54200",
        "name": "Slope 30\u00b0 1 x 1 x 2/3 (Cheese Slope)",
        "part_cat_id": 3,
        "part_url": "https://rebrickable.com/parts/54200/slope-30-1-x-1-x-23-cheese-slope/",
        "part_img_url": "https://cdn.rebrickable.com/media/parts/elements/4244370.jpg",
        "external_ids": {
          "BrickLink": [
            "54200"
          ],
          "BrickOwl": [
            "158788"
          ],
          "Brickset": [
            "18862",
            "33847",
            "35338",
            "50746",
            "54200",
            "63290"
          ],
          "LDraw": [
            "54200"
          ],
          "LEGO": [
            "18862",
            "33847",
            "35338",
            "50746",
            "54200",
            "63290"
          ]
        },
        "print_of": null
      },
      "color": {
        "id": 15,
        "name": "White",
        "rgb": "FFFFFF",
        "is_trans": false
      },
      "set_num": "40010-1",
      "quantity": 1,
      "is_spare": true,
      "element_id": "6550179",
      "num_sets": 830
    },
    {
      "id": 820374,
      "inv_part_id": 820374,
      "part": {
        "part_num": "54200",
        "name": "Slope 30\u00b0 1 x 1 x 2/3 (Cheese Slope)",
        "part_cat_id": 3,
        "part_url": "https://rebrickable.com/parts/54200/slope-30-1-x-1-x-23-cheese-slope/",
        "part_img_url": "https://cdn.rebrickable.com/media/parts/elements/4244370.jpg",
        "external_ids": {
          "BrickLink": [
            "54200"
          ],
          "BrickOwl": [
            "158788"
          ],
          "Brickset": [
            "18862",
            "33847",
            "35338",
            "50746",
            "54200",
            "63290"
          ],
          "LDraw": [
            "54200"
          ],
          "LEGO": [
            "18862",
            "33847",
            "35338",
            "50746",
            "54200",
            "63290"
          ]
        },
        "print_of": null
      },
      "color": {
        "id": 15,
        "name": "White",
        "rgb": "FFFFFF",
        "is_trans": false
      },
      "set_num": "40010-1",
      "quantity": 1,
      "is_spare": false,
      "element_id": "6550179",
      "num_sets": 830
    },
    {
      "id": 626259,
      "inv_part_id": 626259,
      "part": {
        "part_num": "41770",
        "name": "Wedge Plate 4 x 2 Left",
        "part_cat_id": 49,
        "part_url": "https://rebrickable.com/parts/41770/wedge-plate-4-x-2-left/",
        "part_img_url": "https://cdn.rebrickable.com/media/parts/elements/4205470.jpg",
        "external_ids": {
          "BrickLink": [
            "41770"
          ],
          "BrickOwl": [
            "44432"
          ],
          "Brickset": [
            "41770",
            "63333"
          ],
          "LDraw": [
            "41770"
          ],
          "LEGO": [
            "41770",
            "63333"
          ]
        },
        "print_of": null
      },
      "color": {
        "id": 70,
        "name": "Reddish Brown",
        "rgb": "582A12",
        "is_trans": false
      },
      "set_num": "40010-1",
      "quantity": 1,
      "is_spare": false,
      "element_id": "4205470",
      "num_sets": 89
    },
    {
      "id": 212900,
      "inv_part_id": 212900,
      "part": {
        "part_num": "3665",
        "name": "Slope Inverted 45\u00b0 2 x 1",
        "part_cat_id": 3,
        "part_url": "https://rebrickable.com/parts/3665/slope-inverted-45-2-x-1/",
        "part_img_url": "https://cdn.rebrickable.com/media/parts/elements/366521.jpg",
        "external_ids": {
          "BrickLink": [
            "3665"
          ],
          "BrickOwl": [
            "320373"
          ],
          "Brickset": [
            "3665"
          ],
          "LDraw": [
            "3665a",
            "3665b"
          ],
          "LEGO": [
            "3665"
          ]
        },
        "print_of": null
      },
      "color": {
        "id": 4,
        "name": "Red",
        "rgb": "C91A09",
        "is_trans": false
      },
      "set_num": "40010-1",
      "quantity": 3,
      "is_spare": false,
      "element_id": "366521",
      "num_sets": 386
    },
    {
      "id": 373953,
      "inv_part_id": 373953,
      "part": {
        "part_num": "48729b",
        "name": "Bar 1L with Clip [Cut Edges and One Side Hole] [Gap in Clip]",
        "part_cat_id": 32,
        "part_url": "https://rebrickable.com/parts/48729b/bar-1l-with-clip-cut-edges-and-one-side-hole-gap-in-clip/",
        "part_img_url": "https://cdn.rebrickable.com/media/parts/elements/4289538.jpg",
        "external_ids": {
          "BrickLink": [
            "48729b"
          ],
          "BrickOwl": [
            "664516"
          ],
          "Brickset": [
            "41005",
            "48729",
            "55529",
            "86022",
            "88428"
          ],
          "LDraw": [
            "48729b"
          ],
          "LEGO": [
            "41005",
            "48729",
            "55529",
            "86022",
            "88428"
          ]
        },
        "print_of": null
      },
      "color": {
        "id": 0,
        "name": "Black",
        "rgb": "05131D",
        "is_trans": false
      },
      "set_num": "40010-1",
      "quantity": 2,
      "is_spare": false,
      "element_id": "6278152",
      "num_sets": 399
    },
    {
      "id": 394618,
      "inv_part_id": 394618,
      "part": {
        "part_num": "3623",
        "name": "Plate 1 x 3",
        "part_cat_id": 14,
        "part_url": "https://rebrickable.com/parts/3623/plate-1-x-3/",
        "part_img_url": "https://cdn.rebrickable.com/media/parts/elements/362324.jpg",
        "external_ids": {
          "BrickLink": [
            "3623"
          ],
          "BrickOwl": [
            "212990"
          ],
          "Brickset": [
            "3623"
          ],
          "LDraw": [
            "3623"
          ],
          "LEGO": [
            "3623"
          ]
        },
        "print_of": null
      },
      "color": {
        "id": 14,
        "name": "Yellow",
        "rgb": "F2CD37",
        "is_trans": false
      },
      "set_num": "40010-1",
      "quantity": 2,
      "is_spare": false,
      "element_id": "362324",
      "num_sets": 430
    },
    {
      "id": 624689,
      "inv_part_id": 624689,
      "part": {
        "part_num": "3623",
        "name": "Plate 1 x 3",
        "part_cat_id": 14,
        "part_url": "https://rebrickable.com/parts/3623/plate-1-x-3/",
        "part_img_url": "https://cdn.rebrickable.com/media/parts/elements/4211133.jpg",
        "external_ids": {
          "BrickLink": [
            "3623"
          ],
          "BrickOwl": [
            "212990"
          ],
          "Brickset": [
            "3623"
          ],
          "LDraw": [
            "3623"
          ],
          "LEGO": [
            "3623"
          ]
        },
        "print_of": null
      },
      "color": {
        "id": 72,
        "name": "Dark Bluish Gray",
        "rgb": "6C6E68",
        "is_trans": false
      },
      "set_num": "40010-1",
      "quantity": 2,
      "is_spare": false,
      "element_id": "4211133",
      "num_sets": 657
    },
    {
      "id": 480522,
      "inv_part_id": 480522,
      "part": {
        "part_num": "3005",
        "name": "Brick 1 x 1",
        "part_cat_id": 11,
        "part_url": "https://rebrickable.com/parts/3005/brick-1-x-1/",
        "part_img_url": "https://cdn.rebrickable.com/media/parts/elements/4211242.jpg",
        "external_ids": {
          "BrickLink": [
            "3005"
          ],
          "BrickOwl": [
            "656416"
          ],
          "Brickset": [
            "3005",
            "30071",
            "35382"
          ],
          "LDraw": [
            "3005",
            "30071"
          ],
          "LEGO": [
            "3005",
            "30071",
            "35382"
          ]
        },
        "print_of": null
      },
      "color": {
        "id": 70,
        "name": "Reddish Brown",
        "rgb": "582A12",
        "is_trans": false
      },
      "set_num": "40010-1",
      "quantity": 3,
      "is_spare": false,
      "element_id": "4211242",
      "num_sets": 422
    },
    {
      "id": 849908,
      "inv_part_id": 849908,
      "part": {
        "part_num": "3710",
        "name": "Plate 1 x 4",
        "part_cat_id": 14,
        "part_url": "https://rebrickable.com/parts/3710/plate-1-x-4/",
        "part_img_url": "https://cdn.rebrickable.com/media/parts/elements/4211190.jpg",
        "external_ids": {
          "BrickLink": [
            "3710"
          ],
          "BrickOwl": [
            "515555"
          ],
          "Brickset": [
            "3710"
          ],
          "LDraw": [
            "3710"
          ],
          "LEGO": [
            "3710"
          ]
        },
        "print_of": null
      },
      "color": {
        "id": 70,
        "name": "Reddish Brown",
        "rgb": "582A12",
        "is_trans": false
      },
      "set_num": "40010-1",
      "quantity": 2,
      "is_spare": false,
      "element_id": "4211190",
      "num_sets": 708
    },
    {
      "id": 933161,
      "inv_part_id": 933161,
      "part": {
        "part_num": "3022",
        "name": "Plate 2 x 2",
        "part_cat_id": 14,
        "part_url": "https://rebrickable.com/parts/3022/plate-2-x-2/",
        "part_img_url": "https://cdn.rebrickable.com/media/parts/elements/302226.jpg",
        "external_ids": {
          "BrickLink": [
            "3022"
          ],
          "BrickOwl": [
            "566026"
          ],
          "Brickset": [
            "3022",
            "94148"
          ],
          "LDraw": [
            "3022",
            "94148"
          ],
          "LEGO": [
            "3022",
            "94148"
          ]
        },
        "print_of": null
      },
      "color": {
        "id": 0,
        "name": "Black",
        "rgb": "05131D",
        "is_trans": false
      },
      "set_num": "40010-1",
      "quantity": 1,
      "is_spare": false,
      "element_id": "302226",
      "num_sets": 2118
    },
    {
      "id": 544377,
      "inv_part_id": 544377,
      "part": {
        "part_num": "6141",
        "name": "Plate Round 1 x 1 with Solid Stud",
        "part_cat_id": 21,
        "part_url": "https://rebrickable.com/parts/6141/plate-round-1-x-1-with-solid-stud/",
        "part_img_url": "https://cdn.rebrickable.com/media/parts/elements/614124.jpg",
        "external_ids": {
          "BrickLink": [
            "4073"
          ],
          "BrickOwl": [
            "961948"
          ],
          "Brickset": [
            "15570",
            "30057",
            "34823",
            "39799",
            "44325",
            "6141"
          ],
          "LDraw": [
            "4073",
            "6141"
          ],
          "LEGO": [
            "15570",
            "30057",
            "34823",
            "39799",
            "44325",
            "51809",
            "6141"
          ],
          "Peeron": [
            "4073"
          ]
        },
        "print_of": null
      },
      "color": {
        "id": 14,
        "name": "Yellow",
        "rgb": "F2CD37",
        "is_trans": false
      },
      "set_num": "40010-1",
      "quantity": 1,
      "is_spare": true,
      "element_id": "614124",
      "num_sets": 609
    },
    {
      "id": 731149,
      "inv_part_id": 731149,
      "part": {
        "part_num": "6141",
        "name": "Plate Round 1 x 1 with Solid Stud",
        "part_cat_id": 21,
        "part_url": "https://rebrickable.com/parts/6141/plate-round-1-x-1-with-solid-stud/",
        "part_img_url": "https://cdn.rebrickable.com/media/parts/elements/614126.jpg",
        "external_ids": {
          "BrickLink": [
            "4073"
          ],
          "BrickOwl": [
            "961948"
          ],
          "Brickset": [
            "15570",
            "30057",
            "34823",
            "39799",
            "44325",
            "6141"
          ],
          "LDraw": [
            "4073",
            "6141"
          ],
          "LEGO": [
            "15570",
            "30057",
            "34823",
            "39799",
            "44325",
            "51809",
            "6141"
          ],
          "Peeron": [
            "4073"
          ]
        },
        "print_of": null
      },
      "color": {
        "id": 0,
        "name": "Black",
        "rgb": "05131D",
        "is_trans": false
      },
      "set_num": "40010-1",
      "quantity": 1,
      "is_spare": true,
      "element_id": "614126",
      "num_sets": 1352
    },
    {
      "id": 910404,
      "inv_part_id": 910404,
      "part": {
        "part_num": "6141",
        "name": "Plate Round 1 x 1 with Solid Stud",
        "part_cat_id": 21,
        "part_url": "https://rebrickable.com/parts/6141/plate-round-1-x-1-with-solid-stud/",
        "part_img_url": "https://cdn.rebrickable.com/media/parts/elements/614101.jpg",
        "external_ids": {
          "BrickLink": [
            "4073"
          ],
          "BrickOwl": [
            "961948"
          ],
          "Brickset": [
            "15570",
            "30057",
            "34823",
            "39799",
            "44325",
            "6141"
          ],
          "LDraw": [
            "4073",
            "6141"
          ],
          "LEGO": [
            "15570",
            "30057",
            "34823",
            "39799",
            "44325",
            "51809",
            "6141"
          ],
          "Peeron": [
            "4073"
          ]
        },
        "print_of": null
      },
      "color": {
        "id": 15,
        "name": "White",
        "rgb": "FFFFFF",
        "is_trans": false
      },
      "set_num": "40010-1",
      "quantity": 1,
      "is_spare": true,
      "element_id": "614101",
      "num_sets": 1007
    },
    {
      "id": 435223,
      "inv_part_id": 435223,
      "part": {
        "part_num": "3024",
        "name": "Plate 1 x 1",
        "part_cat_id": 14,
        "part_url": "https://rebrickable.com/parts/3024/plate-1-x-1/",
        "part_img_url": "https://cdn.rebrickable.com/media/parts/elements/302401.jpg",
        "external_ids": {
          "BrickLink": [
            "3024"
          ],
          "BrickOwl": [
            "322944"
          ],
          "Brickset": [
            "28554",
            "30008",
            "3024",
            "63326"
          ],
          "LDraw": [
            "3024"
          ],
          "LEGO": [
            "28554",
            "30008",
            "3024",
            "63326"
          ],
          "Peeron": [
            "30008"
          ]
        },
        "print_of": null
      },
      "color": {
        "id": 15,
        "name": "White",
        "rgb": "FFFFFF",
        "is_trans": false
      },
      "set_num": "40010-1",
      "quantity": 6,
      "is_spare": false,
      "element_id": "6548262",
      "num_sets": 1321
    },
    {
      "id": 83358,
      "inv_part_id": 83358,
      "part": {
        "part_num": "3024",
        "name": "Plate 1 x 1",
        "part_cat_id": 14,
        "part_url": "https://rebrickable.com/parts/3024/plate-1-x-1/",
        "part_img_url": "https://cdn.rebrickable.com/media/parts/elements/4210719.jpg",
        "external_ids": {
          "BrickLink": [
            "3024"
          ],
          "BrickOwl": [
            "322944"
          ],
          "Brickset": [
            "28554",
            "30008",
            "3024",
            "63326"
          ],
          "LDraw": [
            "3024"
          ],
          "LEGO": [
            "28554",
            "30008",
            "3024",
            "63326"
          ],
          "Peeron": [
            "30008"
          ]
        },
        "print_of": null
      },
      "color": {
        "id": 72,
        "name": "Dark Bluish Gray",
        "rgb": "6C6E68",
        "is_trans": false
      },
      "set_num": "40010-1",
      "quantity": 2,
      "is_spare": false,
      "element_id": "4210719",
      "num_sets": 604
    },
    {
      "id": 252897,
      "inv_part_id": 252897,
      "part": {
        "part_num": "4865a",
        "name": "Panel 1 x 2 x 1 [Square Corners]",
        "part_cat_id": 23,
        "part_url": "https://rebrickable.com/parts/4865a/panel-1-x-2-x-1-square-corners/",
        "part_img_url": "https://cdn.rebrickable.com/media/parts/ldraw/4/4865a.png",
        "external_ids": {
          "BrickLink": [
            "4865"
          ],
          "BrickOwl": [
            "746621"
          ],
          "Brickset": [
            "30010",
            "4865"
          ],
          "LDraw": [
            "4865a"
          ],
          "LEGO": [
            "30010",
            "4865"
          ],
          "Peeron": [
            "4865"
          ]
        },
        "print_of": null
      },
      "color": {
        "id": 4,
        "name": "Red",
        "rgb": "C91A09",
        "is_trans": false
      },
      "set_num": "40010-1",
      "quantity": 1,
      "is_spare": false,
      "element_id": null,
      "num_sets": 139
    },
    {
      "id": 924764,
      "inv_part_id": 924764,
      "part": {
        "part_num": "3023",
        "name": "Plate 1 x 2",
        "part_cat_id": 14,
        "part_url": "https://rebrickable.com/parts/3023/plate-1-x-2/",
        "part_img_url": "https://cdn.rebrickable.com/media/parts/elements/302305.jpg",
        "external_ids": {
          "BrickLink": [
            "3023"
          ],
          "BrickOwl": [
            "44980"
          ],
          "Brickset": [
            "28653",
            "3023",
            "6225"
          ],
          "LDraw": [
            "28653",
            "3023b"
          ],
          "LEGO": [
            "28653",
            "3023",
            "6225"
          ]
        },
        "print_of": null
      },
      "color": {
        "id": 19,
        "name": "Tan",
        "rgb": "E4CD9E",
        "is_trans": false
      },
      "set_num": "40010-1",
      "quantity": 2,
      "is_spare": false,
      "element_id": "4113917",
      "num_sets": 1027
    },
    {
      "id": 557001,
      "inv_part_id": 557001,
      "part": {
        "part_num": "3040b",
        "name": "Slope 45\u00b0 2 x 1 with Bottom Pin",
        "part_cat_id": 3,
        "part_url": "https://rebrickable.com/parts/3040b/slope-45-2-x-1-with-bottom-pin/",
        "part_img_url": "https://cdn.rebrickable.com/media/parts/elements/304021.jpg",
        "external_ids": {
          "BrickLink": [
            "3040"
          ],
          "BrickOwl": [
            "735007"
          ],
          "Brickset": [
            "3040",
            "35281",
            "6270"
          ],
          "LDraw": [
            "3040b"
          ],
          "LEGO": [
            "3040",
            "35281",
            "6270"
          ]
        },
        "print_of": null
      },
      "color": {
        "id": 4,
        "name": "Red",
        "rgb": "C91A09",
        "is_trans": false
      },
      "set_num": "40010-1",
      "quantity": 1,
      "is_spare": false,
      "element_id": "4121934",
      "num_sets": 477
    }
  ]
}